byuoauth/__init__.py
byuoauth/cred_manager.py
byuoauth/jwt_client.py
byuoauth/token_client.py
byuoauth-2.8.dist-info/LICENSE
byuoauth-2.8.dist-info/METADATA
byuoauth-2.8.dist-info/WHEEL
byuoauth-2.8.dist-info/top_level.txt
byuoauth-2.8.dist-info/RECORD
